powerschool/__init__.py
powerschool/client.py
powerschool/utils.py
powerschool-4.0.1.dist-info/WHEEL
powerschool-4.0.1.dist-info/METADATA
powerschool-4.0.1.dist-info/licenses/LICENSE
powerschool-4.0.1.dist-info/RECORD
