Metadata-Version: 2.1
Name: powerschool
Version: 4.0.1
Summary: Python client for the PowerSchool API
License: GPL-3.0-or-later
Author-email: Charlie Bini <5003326+cbini@users.noreply.github.com>
Requires-Python: >=3.7
Requires-Dist: fiql-parser>=0.15
Requires-Dist: oauthlib>=3.2.2
Requires-Dist: python-dateutil>=2.8.2
Requires-Dist: requests-oauthlib>=1.3.1
Requires-Dist: requests>=2.28.1
Project-URL: homepage, https://github.com/TEAMSchools/powerschool
Project-URL: repository, https://github.com/TEAMSchools/powerschool
